yaml2pac.py
yaml2pac-0.1.0.dist-info/DESCRIPTION.rst
yaml2pac-0.1.0.dist-info/METADATA
yaml2pac-0.1.0.dist-info/metadata.json
yaml2pac-0.1.0.dist-info/RECORD
yaml2pac-0.1.0.dist-info/top_level.txt
yaml2pac-0.1.0.dist-info/WHEEL
