Metadata-Version: 2.0
Name: yaml2pac
Version: 0.1.0
Summary: Generate decent pac file from a set of yaml rules
Home-page: https://github.com/reorx/yaml2pac
Author: reorx
Author-email: novoreorx@gmail.com
License: UNKNOWN
Platform: UNKNOWN
Requires-Dist: PyYAML
